pook/__init__.py
pook/activate_async.py
pook/api.py
pook/assertion.py
pook/compare.py
pook/constants.py
pook/engine.py
pook/exceptions.py
pook/headers.py
pook/helpers.py
pook/matcher.py
pook/mock.py
pook/mock_engine.py
pook/pytest_fixture.py
pook/regex.py
pook/request.py
pook/response.py
pook/interceptors/__init__.py
pook/interceptors/_httpx.py
pook/interceptors/aiohttp.py
pook/interceptors/base.py
pook/interceptors/http.py
pook/interceptors/urllib3.py
pook/matchers/__init__.py
pook/matchers/api.py
pook/matchers/base.py
pook/matchers/body.py
pook/matchers/headers.py
pook/matchers/json.py
pook/matchers/json_schema.py
pook/matchers/method.py
pook/matchers/path.py
pook/matchers/query.py
pook/matchers/url.py
pook/matchers/xml.py
pook-2.1.4.dist-info/METADATA
pook-2.1.4.dist-info/WHEEL
pook-2.1.4.dist-info/entry_points.txt
pook-2.1.4.dist-info/licenses/LICENSE
pook-2.1.4.dist-info/RECORD
