Metadata-Version: 2.4
Name: pook
Version: 2.1.4
Summary: HTTP traffic mocking and expectations made easy
Project-URL: Homepage, https://github.com/h2non/pook
Author-email: Tomas Aparicio <tomas@aparicio.me>, Sara Marcondes <git@sarayourfriend.pictures>
License-Expression: MIT
License-File: LICENSE
Classifier: Development Status :: 5 - Production/Stable
Classifier: Intended Audience :: Developers
Classifier: Intended Audience :: System Administrators
Classifier: License :: OSI Approved :: MIT License
Classifier: Natural Language :: English
Classifier: Operating System :: OS Independent
Classifier: Programming Language :: Python :: 3.9
Classifier: Programming Language :: Python :: 3.10
Classifier: Programming Language :: Python :: 3.11
Classifier: Programming Language :: Python :: 3.12
Classifier: Programming Language :: Python :: 3.13
Classifier: Programming Language :: Python :: Implementation :: CPython
Classifier: Programming Language :: Python :: Implementation :: PyPy
Classifier: Topic :: Software Development
Classifier: Topic :: Software Development :: Libraries :: Python Modules
Requires-Python: >=3.9
Requires-Dist: furl>=0.5.6
Requires-Dist: jsonschema>=2.5.1
Requires-Dist: xmltodict>=0.11.0
